{
  "Tri-Horned Dragon": [
    "Normal Parallel Rare"
  ],
  "Malefic Blue-Eyes White Dragon": [
    "Normal Parallel Rare"
  ],
  "Anti-Spell Fragrance": [
    "Normal Parallel Rare"
  ],
  "Vampire's Curse": [
    "Common"
  ],
  "Felgrand Dragon": [
    "Common"
  ],
  "Decoy Dragon": [
    "Common"
  ],
  "Owner's Seal": [
    "Common"
  ],
  "Overpowering Eye": [
    "Common"
  ],
  "Winning Formula": [
    "Common"
  ],
  "Special Phase Card": [
    "Common"
  ]
}