{
  "Token (Tea and \"Dark Magician Girl\")": [
    "Super Rare"
  ],
  "Token (Luna and \"Ancient Fairy Dragon\")": [
    "Super Rare"
  ],
  "Token (Playmaker and Ai and \"Decode Talker\")": [
    "Super Rare"
  ],
  "Token (Playmaker and Cyberse Quantum Dragon)": [
    "Super Rare"
  ],
  "Token (Ai and \"The Arrival Cyberse @Ignister\")": [
    "Super Rare"
  ],
  "Dragon Master Lords": [
    "Quarter Century Secret Rare"
  ],
  "Wizard @Ignister": [
    "Super Rare"
  ],
  "Backup @Ignister": [
    "Ultra Rare, Quarter Century Secret Rare"
  ],
  "Kurikurinku @Ignister": [
    "Common"
  ],
  "Dark Magician Girl the Magician's Apprentice": [
    "Secret Rare, Quarter Century Secret Rare"
  ],
  "Evil HERO Vicious Claws": [
    "Common"
  ],
  "Regulus the Fairy Beast": [
    "Common"
  ],
  "Spore the Fairy Seed": [
    "Common"
  ],
  "Kuribon the Fairy Spirit": [
    "Common"
  ],
  "Heraldic Beast Gryphon": [
    "Super Rare"
  ],
  "Heraldic Beast Stad Whale": [
    "Common"
  ],
  "Diabellstar Vengeance": [
    "Secret Rare, Quarter Century Secret Rare"
  ],
  "Diabellze the White Witch": [
    "Super Rare"
  ],
  "Regenesis Warrior": [
    "Common"
  ],
  "Regenesis Sage": [
    "Ultra Rare, Quarter Century Secret Rare"
  ],
  "Regenesis Dragon": [
    "Common"
  ],
  "Regenesis Archfiend": [
    "Secret Rare, Quarter Century Secret Rare"
  ],
  "Regenesis Lord": [
    "Ultra Rare, Quarter Century Secret Rare"
  ],
  "Spectral, Dragon Ruler of Flickers": [
    "Ultra Rare, Quarter Century Secret Rare"
  ],
  "Nebulus, Dragon Ruler of Mishaps": [
    "Ultra Rare, Quarter Century Secret Rare"
  ],
  "Argostars - Fierce Parthe": [
    "Super Rare"
  ],
  "Prima Materiactor": [
    "Common"
  ],
  "Star Ryzeal": [
    "Secret Rare, Quarter Century Secret Rare"
  ],
  "Maliss P March Hare": [
    "Secret Rare, Quarter Century Secret Rare"
  ],
  "Tensei Ryu-Ge Anva": [
    "Common"
  ],
  "Red-Eyes Metal Claws Dragon": [
    "Super Rare"
  ],
  "Cyber Jormungardr": [
    "Common"
  ],
  "Cyberdark Wurm": [
    "Ultra Rare, Quarter Century Secret Rare"
  ],
  "Live☆Twin Lil-la Sweet": [
    "Ultra Rare, Quarter Century Secret Rare"
  ],
  "Moissa Wight": [
    "Common"
  ],
  "NT8000 - SIRIUS": [
    "Common"
  ],
  "Wicked Serpent Night Dragon": [
    "Common"
  ],
  "Crimson Firewing Pegasus": [
    "Common"
  ],
  "Brain Controller": [
    "Common"
  ],
  "Bomber Place": [
    "Common"
  ],
  "Azamina (card)": [
    "Super Rare"
  ],
  "Fallen Angel of the Golden Land": [
    "Ultra Rare, Quarter Century Secret Rare"
  ],
  "Filia Regis": [
    "Super Rare"
  ],
  "Firewall Saber Dragon": [
    "Super Rare"
  ],
  "Ancient Fairy Life Dragon": [
    "Super Rare"
  ],
  "Snake-Eyes Vengeance Dragon": [
    "Ultra Rare, Quarter Century Secret Rare"
  ],
  "Poplar of the White Forest": [
    "Super Rare"
  ],
  "Legendary Lord Six Samurai - Kizan": [
    "Common"
  ],
  "Juraishin, the Cursed Thunder God": [
    "Ultra Rare, Quarter Century Secret Rare"
  ],
  "Code Igniter": [
    "Common"
  ],
  "Number 69: Heraldry Crest - Shatter Stream": [
    "Common"
  ],
  "Number 69: Heraldry Crest - Dark Matter Demolition": [
    "Ultra Rare, Quarter Century Secret Rare"
  ],
  "Chasma, Dragon Ruler of Auroras": [
    "Secret Rare, Quarter Century Secret Rare"
  ],
  "Eclipse, Dragon Ruler of Catastrophes": [
    "Ultra Rare, Quarter Century Secret Rare"
  ],
  "Disaster, Dragon Ruler of All Apocalypses": [
    "Ultra Rare, Quarter Century Secret Rare"
  ],
  "Steamed Sabersaurus": [
    "Common"
  ],
  "Allied Code Talker @Ignister": [
    "Secret Rare, Quarter Century Secret Rare"
  ],
  "Evil★Twin Ki-sikil Deal": [
    "Super Rare"
  ],
  "Dogurad, the Stonetrooper": [
    "Common"
  ],
  "A.I. Connect": [
    "Super Rare"
  ],
  "World of Spirits": [
    "Super Rare"
  ],
  "Flash of Heraldry": [
    "Super Rare"
  ],
  "Filia Diabell": [
    "Common"
  ],
  "Witch of the White Forest": [
    "Ultra Rare, Quarter Century Secret Rare"
  ],
  "Regenesis (card)": [
    "Secret Rare, Quarter Century Secret Rare"
  ],
  "Regenesis Code": [
    "Super Rare"
  ],
  "Here There Be Dragons": [
    "Common"
  ],
  "Argostars - Giantslaying": [
    "Super Rare"
  ],
  "Materiactor Meltthrough": [
    "Common"
  ],
  "Maliss in the Mirror": [
    "Super Rare"
  ],
  "Wight Reanimator": [
    "Common"
  ],
  "Gordian Slicer": [
    "Secret Rare, Quarter Century Secret Rare"
  ],
  "Chaotic Elements": [
    "Common"
  ],
  "Let's Go Together": [
    "Common"
  ],
  "Seven Stars Slash - Army Annihilator Hagun": [
    "Common"
  ],
  "SA.I.dekick": [
    "Common"
  ],
  "Eternal Sunshine": [
    "Common"
  ],
  "Curse of Diabell": [
    "Common"
  ],
  "Sinful Spoils Sanctification": [
    "Common"
  ],
  "Regenesis Birth": [
    "Common"
  ],
  "Ryzeal Mass Driver": [
    "Common"
  ],
  "Ryu-Ge End": [
    "Common"
  ],
  "Eldlixir of the Glorious Golden Land": [
    "Super Rare"
  ],
  "Songs of the Dominators": [
    "Secret Rare, Quarter Century Secret Rare"
  ],
  "Dragon's Mind": [
    "Common"
  ],
  "Abduction": [
    "Super Rare"
  ],
  "Dawn Angel Kambi": [
    "Common"
  ],
  "Hrimnir the Divine Follower": [
    "Common"
  ],
  "Vingolf's Blessing": [
    "Common"
  ],
  "Aspischool": [
    "Common"
  ],
  "Toxic Boxfish": [
    "Super Rare"
  ],
  "Fish and Bids": [
    "Common"
  ],
  "Replicard LAD": [
    "Super Rare"
  ],
  "Sakra Vendirage": [
    "Super Rare"
  ],
  "Tiki Peace": [
    "Common"
  ],
  "Mitsurugi no Mikoto, Aramasa": [
    "Super Rare"
  ],
  "Mitsurugi no Miko, Wousu": [
    "Common"
  ],
  "Ame no Habakiri no Mitsurugi": [
    "Super Rare"
  ],
  "Mitsurugi Mirror": [
    "Common"
  ],
  "Mitsurugi Magatama": [
    "Super Rare"
  ],
  "Mitsurugi Sacred Boundary": [
    "Common"
  ],
  "Mitsurugi Tempest": [
    "Common"
  ],
  "Dipity": [
    "Common"
  ],
  "Giant Kra-Corn": [
    "Common"
  ],
  "Migratory Zereort": [
    "Common"
  ],
  "Dragolithia Kunzite": [
    "Super Rare"
  ]
}