{
  "Jowgen the Spiritualist": [
    "R"
  ],
  "Kycoo the Ghost Destroyer": [
    "R"
  ],
  "Bazoo the Soul-Eater": [
    "R"
  ],
  "Dark Necrofear": [
    "UR"
  ],
  "Soul of Purity and Light": [
    "C"
  ],
  "Aqua Spirit": [
    "C"
  ],
  "The Rock Spirit": [
    "C"
  ],
  "Gilasaurus": [
    "C"
  ],
  "Tornado Bird": [
    "C"
  ],
  "Zombyra the Dark": [
    "C"
  ],
  "Maryokutai": [
    "C"
  ],
  "The Last Warrior from Another Planet": [
    "SR"
  ],
  "Dark Spirit of the Silent": [
    "C"
  ],
  "Royal Command": [
    "R"
  ],
  "Riryoku Field": [
    "R"
  ],
  "Skull Lair": [
    "C"
  ],
  "Graverobber's Retribution": [
    "C"
  ],
  "Destruction Punch": [
    "C"
  ],
  "Blind Destruction": [
    "C"
  ],
  "The Emperor's Holiday": [
    "C"
  ],
  "Destiny Board": [
    "C"
  ],
  "Spirit Message \"I\"": [
    "C"
  ],
  "Spirit Message \"N\"": [
    "C"
  ],
  "Spirit Message \"A\"": [
    "C"
  ],
  "Spirit Message \"L\"": [
    "C"
  ],
  "The Dark Door": [
    "C"
  ],
  "Spiritualism": [
    "R"
  ],
  "Cyclon Laser": [
    "C"
  ],
  "De-Fusion": [
    "C"
  ],
  "Fusion Gate": [
    "R"
  ],
  "Ekibyo Drakmord": [
    "C"
  ],
  "Miracle Dig": [
    "C"
  ],
  "Vengeful Bog Spirit": [
    "C"
  ],
  "Blade Knight": [
    "UR"
  ],
  "Baby Dragon": [
    "C"
  ],
  "Blackland Fire Dragon": [
    "C"
  ],
  "Battle Steer": [
    "C"
  ],
  "Time Wizard": [
    "SR"
  ],
  "Saggi the Dark Clown": [
    "C"
  ],
  "Dragon Piper": [
    "C"
  ],
  "Illusionist Faceless Mage": [
    "C"
  ],
  "Sangan": [
    "R"
  ],
  "Great Moth": [
    "C"
  ],
  "Kuriboh": [
    "R"
  ],
  "Thousand Dragon": [
    "C"
  ],
  "King of Yamimakai": [
    "C"
  ],
  "Catapult Turtle": [
    "SR"
  ],
  "Mystic Horseman": [
    "C"
  ],
  "Rabid Horseman": [
    "C"
  ],
  "Crass Clown": [
    "C"
  ],
  "Dream Clown": [
    "C"
  ],
  "Princess of Tsurugi": [
    "C"
  ],
  "Tremendous Fire": [
    "C"
  ],
  "Jirai Gumo": [
    "C"
  ],
  "Shadow Ghoul": [
    "C"
  ],
  "Ryu-Kishin Powered": [
    "C"
  ],
  "Launcher Spider": [
    "C"
  ],
  "Thunder Dragon": [
    "C"
  ],
  "The Immortal of Thunder": [
    "C"
  ],
  "Hoshiningen": [
    "C"
  ],
  "Cannon Soldier": [
    "SR"
  ],
  "Muka Muka": [
    "C"
  ],
  "The Bistro Butcher": [
    "C"
  ],
  "Star Boy": [
    "C"
  ],
  "Milus Radiant": [
    "C"
  ],
  "Witch of the Black Forest": [
    "R"
  ],
  "Little Chimera": [
    "C"
  ],
  "Bladefly": [
    "C"
  ],
  "Twin-Headed Thunder Dragon": [
    "C"
  ],
  "Witch's Apprentice": [
    "C"
  ],
  "Gazelle the King of Mythical Beasts": [
    "C"
  ],
  "Barrel Dragon": [
    "UR"
  ],
  "Solemn Judgment": [
    "SR"
  ],
  "Magic Jammer": [
    "SR"
  ],
  "Seven Tools of the Bandit": [
    "SR"
  ],
  "Horn of Heaven": [
    "R"
  ],
  "Shield & Sword": [
    "C"
  ],
  "Block Attack": [
    "C"
  ],
  "The Unhappy Maiden": [
    "C"
  ],
  "Robbin' Goblin": [
    "C"
  ],
  "Mirror Force": [
    "SR"
  ],
  "Ring of Magnetism": [
    "R"
  ],
  "Share the Pain": [
    "C"
  ],
  "Heavy Storm": [
    "SR"
  ],
  "Wattkid": [
    "C"
  ],
  "Soul of the Pure": [
    "C"
  ],
  "Dark-Piercing Light": [
    "C"
  ],
  "The Statue of Easter Island": [
    "C"
  ],
  "Shining Friendship": [
    "C"
  ],
  "The Wicked Worm Beast": [
    "C"
  ],
  "Tiger Axe": [
    "C"
  ],
  "Axe Raider": [
    "C"
  ],
  "Mechanicalchaser": [
    "C"
  ],
  "Gemini Elf": [
    "C"
  ],
  "Graceful Charity": [
    "R"
  ],
  "Two-Headed King Rex": [
    "C"
  ],
  "Goddess with the Third Eye": [
    "C"
  ],
  "Lord of the Lamp": [
    "C"
  ],
  "Machine King": [
    "C"
  ],
  "Cyber-Stein": [
    "R"
  ],
  "Dragon Seeker": [
    "C"
  ],
  "Needle Worm": [
    "C"
  ],
  "Greenkappa": [
    "C"
  ],
  "Morphing Jar": [
    "R"
  ],
  "Penguin Soldier": [
    "R"
  ],
  "Royal Decree": [
    "SR"
  ],
  "Magical Thorn": [
    "C"
  ],
  "Restructer Revolution": [
    "C"
  ],
  "Fusion Sage": [
    "C"
  ],
  "Total Defense Shogun": [
    "SR"
  ],
  "Swift Gaia the Fierce Knight": [
    "UR"
  ],
  "Obnoxious Celtic Guard": [
    "UR"
  ],
  "Luminous Soldier": [
    "C"
  ],
  "Command Knight": [
    "SR"
  ],
  "Kaiser Sea Horse": [
    "C"
  ],
  "Vampire Lord": [
    "UR"
  ],
  "Toon Goblin Attack Force": [
    "C"
  ],
  "Toon Cannon Soldier": [
    "C"
  ],
  "Toon Gemini Elf": [
    "C"
  ],
  "Toon Masked Sorcerer": [
    "C"
  ],
  "Toon Table of Contents": [
    "C"
  ],
  "Toon Defense": [
    "C"
  ],
  "Insect Queen": [
    "UR"
  ],
  "Dark Ruler Ha Des": [
    "UR"
  ],
  "Dark Balter the Terrible": [
    "R"
  ],
  "Lesser Fiend": [
    "C"
  ],
  "Possessed Dark Soul": [
    "C"
  ],
  "Winged Minion": [
    "C"
  ],
  "Skull Knight #2": [
    "C"
  ],
  "Twin-Headed Wolf": [
    "C"
  ],
  "Opticlops": [
    "C"
  ],
  "Bark of Dark Ruler": [
    "C"
  ],
  "Fatal Abacus": [
    "C"
  ],
  "The Puppet Magic of Dark Ruler": [
    "C"
  ],
  "Soul Demolition": [
    "C"
  ],
  "Double Snare": [
    "C"
  ],
  "Freed the Matchless General": [
    "UR"
  ],
  "Marauding Captain": [
    "R"
  ],
  "Ryu Senshi": [
    "R"
  ],
  "Warrior Dai Grepher": [
    "C"
  ],
  "Mysterious Guard": [
    "C"
  ],
  "Frontier Wiseman": [
    "C"
  ],
  "Exiled Force": [
    "C"
  ],
  "Shadow Tamer": [
    "C"
  ],
  "Dragon Manipulator": [
    "C"
  ],
  "The A. Forces": [
    "C"
  ],
  "Reinforcement of the Army": [
    "R"
  ],
  "Array of Revealing Light": [
    "C"
  ],
  "The Warrior Returning Alive": [
    "C"
  ],
  "Emergency Provisions": [
    "R"
  ],
  "Tyrant Dragon": [
    "UR"
  ],
  "Spear Dragon": [
    "SR"
  ],
  "Spirit Ryu": [
    "C"
  ],
  "Fiend Skull Dragon": [
    "R"
  ],
  "Cave Dragon": [
    "C"
  ],
  "Gray Wing": [
    "C"
  ],
  "Troop Dragon": [
    "C"
  ],
  "The Dragon's Bead": [
    "C"
  ],
  "A Wingbeat of Giant Dragon": [
    "C"
  ],
  "Dragon's Gunfire": [
    "C"
  ],
  "Stamping Destruction": [
    "C"
  ],
  "Super Rejuvenation": [
    "C"
  ],
  "Dragon's Rage": [
    "C"
  ],
  "Burst Breath": [
    "C"
  ],
  "Luster Dragon #2": [
    "C"
  ],
  "Fiber Jar": [
    "R"
  ],
  "Serpentine Princess": [
    "C"
  ],
  "Patrician of Darkness": [
    "C"
  ],
  "Thunder Nyan Nyan": [
    "R"
  ],
  "Gradius' Option": [
    "C"
  ],
  "Injection Fairy Lily": [
    "UR"
  ],
  "Woodland Sprite": [
    "C"
  ],
  "Airknight Parshath": [
    "SR"
  ],
  "Twin-Headed Behemoth": [
    "C"
  ],
  "Maharaghi": [
    "C"
  ],
  "Inaba White Rabbit": [
    "C"
  ],
  "Yata-Garasu": [
    "C"
  ],
  "Susa Soldier": [
    "SR"
  ],
  "Yamata Dragon": [
    "SR"
  ],
  "Great Long Nose": [
    "C"
  ],
  "Otohime": [
    "C"
  ],
  "Hino-Kagu-Tsuchi": [
    "UR"
  ],
  "Asura Priest": [
    "C"
  ],
  "Fushi No Tori": [
    "C"
  ],
  "Spring of Rebirth": [
    "C"
  ],
  "Heart of Clear Water": [
    "C"
  ],
  "A Legendary Ocean": [
    "C"
  ],
  "Fusion Sword Murasame Blade": [
    "C"
  ],
  "Smoke Grenade of the Thief": [
    "C"
  ],
  "Creature Swap": [
    "SR"
  ],
  "Spiritual Energy Settle Machine": [
    "C"
  ],
  "Second Coin Toss": [
    "C"
  ],
  "Convulsion of Nature": [
    "C"
  ],
  "The Secret of the Bandit": [
    "C"
  ],
  "After the Struggle": [
    "C"
  ],
  "Magic Reflector": [
    "C"
  ],
  "Blast with Chain": [
    "R"
  ],
  "Disappear": [
    "C"
  ],
  "Bubble Crash": [
    "C"
  ],
  "Royal Oppression": [
    "R"
  ],
  "Bottomless Trap Hole": [
    "C"
  ],
  "Bad Reaction to Simochi": [
    "C"
  ],
  "Ominous Fortunetelling": [
    "C"
  ],
  "Spirit's Invitation": [
    "C"
  ],
  "Drop Off": [
    "C"
  ],
  "Last Turn": [
    "R"
  ],
  "King Tiger Wanghu": [
    "C"
  ],
  "Birdface": [
    "C"
  ],
  "Kryuel": [
    "C"
  ],
  "Arsenal Bug": [
    "C"
  ],
  "Maiden of the Aqua": [
    "C"
  ],
  "Jowls of Dark Demise": [
    "C"
  ],
  "Mucus Yolk": [
    "C"
  ],
  "Moisture Creature": [
    "C"
  ],
  "Gora Turtle": [
    "C"
  ],
  "Sasuke Samurai": [
    "R"
  ],
  "Dark Dust Spirit": [
    "C"
  ],
  "Royal Keeper": [
    "C"
  ],
  "Wandering Mummy": [
    "C"
  ],
  "Great Dezard": [
    "SR"
  ],
  "Swarm of Scarabs": [
    "C"
  ],
  "Swarm of Locusts": [
    "C"
  ],
  "Giant Axe Mummy": [
    "C"
  ],
  "Guardian Sphinx": [
    "UR"
  ],
  "Pyramid Turtle": [
    "R"
  ],
  "Dice Jar": [
    "C"
  ],
  "Dark Scorpion Burglars": [
    "C"
  ],
  "Don Zaloog": [
    "SR"
  ],
  "Fushioh Richie": [
    "UR"
  ],
  "Book of Life": [
    "SR"
  ],
  "Book of Taiyou": [
    "C"
  ],
  "Book of Moon": [
    "C"
  ],
  "Mirage of Nightmare": [
    "C"
  ],
  "Secret Pass to the Treasures": [
    "C"
  ],
  "Call of the Mummy": [
    "C"
  ],
  "Timidity": [
    "C"
  ],
  "Pyramid Energy": [
    "C"
  ],
  "Tutan Mask": [
    "C"
  ],
  "Ordeal of a Traveler": [
    "C"
  ],
  "Bottomless Shifting Sand": [
    "C"
  ],
  "Curse of Royal": [
    "C"
  ],
  "Needle Ceiling": [
    "C"
  ],
  "Statue of the Wicked": [
    "R"
  ],
  "Dark Coffin": [
    "C"
  ],
  "Needle Wall": [
    "C"
  ],
  "Trap Dustshoot": [
    "C"
  ],
  "Reckless Greed": [
    "C"
  ],
  "Pharaoh's Treasure": [
    "C"
  ],
  "Perfectly Ultimate Great Moth": [
    "UR"
  ],
  "Black Illusion Ritual": [
    "C"
  ],
  "The strategy of Warriors, part 1": [
    "Common"
  ],
  "The strategy of Warriors, part 2": [
    "Common"
  ],
  "\"Blade Knight\"": [
    "Common"
  ],
  "\"Marauding Captain\"": [
    "Common"
  ],
  "\"Total Defense Shogun\"": [
    "Common"
  ],
  "\"Command Knight\"": [
    "Common"
  ],
  "The strategy of Zombies, part 1": [
    "Common"
  ],
  "The strategy of Zombies, part 2": [
    "Common"
  ],
  "\"Ordeal of a Traveler\"": [
    "Common"
  ],
  "Special Summon then Tribute Summon": [
    "Common"
  ],
  "Strategically fill your Graveyard": [
    "Common"
  ],
  "Toon strategy, part 1": [
    "Common"
  ],
  "Toon strategy, part 2": [
    "Common"
  ],
  "Use cards to your advantage": [
    "Common"
  ],
  "Paying Life Point costs": [
    "Common"
  ],
  "\"A Legendary Ocean\"": [
    "Common"
  ],
  "Protect your Effect Monsters": [
    "Common"
  ],
  "Make your opponent discard": [
    "Common"
  ],
  "Depleting your opponent's Deck, part 1": [
    "Common"
  ],
  "Depleting your opponent's Deck, part 2": [
    "Common"
  ],
  "\"Sangan\" and \"Witch of the Black Forest\"": [
    "Common"
  ],
  "\"Dark Necrofear\"": [
    "Common"
  ],
  "Negate your opponent's monster effects": [
    "Common"
  ],
  "Spirit monster combos, part 1": [
    "Common"
  ],
  "Spirit monster combos, part 2": [
    "Common"
  ],
  "Monsters are more than ATK and DEF": [
    "Common"
  ],
  "Make the best of your Main Phase 2": [
    "Common"
  ],
  "Find a monster's weakness": [
    "Common"
  ],
  "\"Reckless Greed\"": [
    "Common"
  ],
  "\"Bottomless Trap Hole\"": [
    "Common"
  ],
  "Other ways to Summon Fusion Monsters": [
    "Common"
  ],
  "The strategy of Dragons, part 1": [
    "Common"
  ],
  "The strategy of Dragons, part 2": [
    "Common"
  ],
  "\"Thunder Dragon\"": [
    "Common"
  ],
  "Cards have multiple uses, part 1": [
    "Common"
  ],
  "Cards have multiple uses, part 2": [
    "Common"
  ],
  "Cards have multiple uses, part 3": [
    "Common"
  ],
  "\"Emergency Provisions\"": [
    "Common"
  ],
  "A \"Mirage of Nightmare\" combo": [
    "Common"
  ],
  "Choosing cards for your Side Deck, part 1": [
    "Common"
  ],
  "Choosing cards for your Side Deck, part 2": [
    "Common"
  ],
  "Choosing cards for your Side Deck, part 3": [
    "Common"
  ],
  "Choosing cards for your Side Deck, part 4": [
    "Common"
  ],
  "Flip Summon with effect": [
    "Common"
  ],
  "\"Fiber Jar\"": [
    "Common"
  ],
  "\"Destiny Board\"": [
    "Common"
  ],
  "\"Last Turn\"": [
    "Common"
  ],
  "Find a fun place to play": [
    "Common"
  ],
  "Ready to compete?": [
    "Common"
  ],
  "The road to the World Championship": [
    "Common"
  ]
}