{
  "Elemental HERO Neos": [
    "Common"
  ],
  "Elemental HERO Bladedge": [
    "Rare"
  ],
  "Elemental HERO Wildheart": [
    "Common"
  ],
  "Hero Kid": [
    "Common"
  ],
  "Neo-Spacian Aqua Dolphin": [
    "Rare"
  ],
  "Neo-Spacian Flare Scarab": [
    "Rare"
  ],
  "Neo-Spacian Dark Panther": [
    "Rare"
  ],
  "Chrysalis Dolphin": [
    "Common"
  ],
  "Card Trooper": [
    "Ultra Rare"
  ],
  "Elemental HERO Wildedge": [
    "Rare"
  ],
  "Elemental HERO Wild Wingman": [
    "Common"
  ],
  "Elemental HERO Aqua Neos": [
    "Rare"
  ],
  "Elemental HERO Flare Neos": [
    "Rare"
  ],
  "Elemental HERO Dark Neos": [
    "Super Rare"
  ],
  "Cyclone Boomerang": [
    "Common"
  ],
  "H - Heated Heart": [
    "Common"
  ],
  "E - Emergency Call": [
    "Common"
  ],
  "R - Righteous Justice": [
    "Common"
  ],
  "O - Oversoul": [
    "Common"
  ],
  "Hero Flash!!": [
    "Common"
  ],
  "Contact": [
    "Common"
  ],
  "Fake Hero": [
    "Common"
  ],
  "Common Soul": [
    "Common"
  ],
  "Neo Space": [
    "Common"
  ],
  "Light Laser": [
    "Super Rare"
  ],
  "Burial from a Different Dimension": [
    "Ultra Rare"
  ],
  "Hero Barrier": [
    "Common"
  ],
  "Miracle Kids": [
    "Common"
  ],
  "Edge Hammer": [
    "Super Rare"
  ],
  "Kid Guard": [
    "Super Rare"
  ],
  "Out-of-this-world \"Neos\" combo": [
    "Common"
  ],
  "The best defense is a good offense": [
    "Common"
  ],
  "\"Neo-Spacian Aqua Dolphin\" Summoning combo": [
    "Common"
  ],
  "Keep the cards coming": [
    "Common"
  ],
  "Crush the competition": [
    "Common"
  ],
  "\"Elemental Hero Sparkman's\" arsenal": [
    "Common"
  ],
  "Multiply your \"Miracle Fusion\"": [
    "Common"
  ],
  "A turnabout play": [
    "Common"
  ],
  "Call your Heroes from your Deck": [
    "Common"
  ],
  "Duelist Pack -JADEN YUKI 2- Checklist": [
    "Common"
  ]
}