{
  "Piwraithe the Ghost Pirate": [
    "C"
  ],
  "Parallel eXceed": [
    "C"
  ],
  "Codebreaker Zero Day": [
    "C"
  ],
  "Salamangreat Zebroid X": [
    "C"
  ],
  "Gouki Iron Claw": [
    "C"
  ],
  "Gouki Guts": [
    "C"
  ],
  "Marincess Basilalima": [
    "C"
  ],
  "Noctovision Dragon": [
    "C"
  ],
  "Archnemeses Protos": [
    "UR"
  ],
  "Archnemeses Eschatos": [
    "UR"
  ],
  "Nemeses Flag": [
    "SR"
  ],
  "Nemeses Umbrella": [
    "SR"
  ],
  "Nemeses Corridor": [
    "SR"
  ],
  "Deep Sea Artisan": [
    "C"
  ],
  "Deep Sea Sentry": [
    "C"
  ],
  "Deep Sea Minstrel": [
    "C"
  ],
  "Red Familiar": [
    "C"
  ],
  "Crimson Resonator": [
    "C"
  ],
  "Lantern Shark": [
    "C"
  ],
  "Buzzsaw Shark": [
    "C"
  ],
  "Ancient Warriors - Ambitious Cao De": [
    "SR"
  ],
  "Ancient Warriors - Fearsome Zhang Yuan": [
    "C"
  ],
  "Ancient Warriors - Deceptive Jia Wen": [
    "C"
  ],
  "Ancient Warriors - Ingenious Zhuge Kong": [
    "SR"
  ],
  "Girsu, the Orcust Mekk-Knight": [
    "ScR"
  ],
  "Thunder Dragonlord": [
    "C"
  ],
  "Chamber Dragonmaid": [
    "ScR, StR"
  ],
  "Harr, Generaider Boss of Storms": [
    "SR"
  ],
  "Loptr, Shadow of the Generaider Bosses": [
    "UR"
  ],
  "Unchained Twins - Sarama": [
    "C"
  ],
  "King Beast Barbaros": [
    "C"
  ],
  "Gizmek Uka, the Festive Fox of Fecundity": [
    "ScR"
  ],
  "Trias Hierarchia": [
    "C"
  ],
  "Cataclysmic Circumpolar Chilblainia": [
    "C"
  ],
  "Union Driver": [
    "UR"
  ],
  "Malice, Lady of Lament": [
    "SR"
  ],
  "Ghost Mourner & Moonlit Chill": [
    "ScR, StR"
  ],
  "Animadorned Archosaur": [
    "ScR"
  ],
  "Goldilocks the Battle Landscaper": [
    "C"
  ],
  "Magical Hound": [
    "C"
  ],
  "Invoked Augoeides": [
    "SR"
  ],
  "Dragonmaid Sheou": [
    "UR"
  ],
  "Deep Sea Prima Donna": [
    "UR"
  ],
  "Ravenous Crocodragon Archethys": [
    "UR"
  ],
  "Valiant Shark Lancer": [
    "SR"
  ],
  "Traptrix Allomerus": [
    "UR, StR"
  ],
  "Accesscode Talker": [
    "ScR"
  ],
  "Proxy F Magician": [
    "C"
  ],
  "Splash Mage": [
    "C"
  ],
  "Linkross": [
    "UR"
  ],
  "The Arrival Cyberse @Ignister": [
    "SR"
  ],
  "Codebreaker Virus Berserker": [
    "C"
  ],
  "Codebreaker Virus Swordsman": [
    "C"
  ],
  "Gouki The Powerload Ogre": [
    "C"
  ],
  "Marincess Great Bubble Reef": [
    "SR"
  ],
  "Eria the Water Charmer, Gentle": [
    "SR, StR"
  ],
  "A.I. Contact": [
    "SR"
  ],
  "Burning Draw": [
    "SR"
  ],
  "Link Burst": [
    "C"
  ],
  "Stairs of Mail": [
    "C"
  ],
  "Nemeses Adrastea": [
    "C"
  ],
  "Deep Sea Aria": [
    "ScR"
  ],
  "Resonator Command": [
    "C"
  ],
  "Torpedo Takedown": [
    "C"
  ],
  "Madolche Salon": [
    "UR"
  ],
  "Void Apocalypse": [
    "SR"
  ],
  "Heavy Forward": [
    "UR"
  ],
  "Witchcrafter Unveiling": [
    "SR"
  ],
  "Evil Eye Reemergence": [
    "C"
  ],
  "Ancient Warriors Saga - Borrowing of Arrows": [
    "C"
  ],
  "Megalith Unformed": [
    "C"
  ],
  "Fusion Deployment": [
    "UR"
  ],
  "Flourishing Frolic": [
    "C"
  ],
  "A.I.Q": [
    "C"
  ],
  "Red Reign": [
    "SR"
  ],
  "Xyz Revive Splash": [
    "C"
  ],
  "Madolche Promenade": [
    "SR"
  ],
  "Witchcrafter Patronus": [
    "SR"
  ],
  "Gravedigger's Trap Hole": [
    "ScR"
  ],
  "Titanocider": [
    "ScR"
  ],
  "Pinpoint Dash": [
    "C"
  ],
  "Rose Girl": [
    "SR"
  ],
  "Scrypton": [
    "SR"
  ],
  "Taotie Dragon": [
    "C"
  ],
  "Necroquip Prism": [
    "C"
  ],
  "Bluebeard, the Plunder Patroll Shipwright": [
    "C"
  ],
  "Goldenhair, the Newest Plunder Patroll": [
    "C"
  ],
  "Plunder Patrollship Lys": [
    "ScR"
  ],
  "Plunder Patroll Shipshape Ships Shipping": [
    "SR"
  ],
  "Emblem of the Plunder Patroll": [
    "UR"
  ],
  "Pride of the Plunder Patroll": [
    "C"
  ],
  "Plunder Patroll Parrrty": [
    "SR"
  ],
  "Superheavy Samurai Wagon": [
    "C"
  ],
  "Rain Bozu": [
    "C"
  ],
  "Performapal Turn Trooper": [
    "C"
  ],
  "Armored Bitron": [
    "SR"
  ],
  "Gussari @Ignister": [
    "SR"
  ],
  "Gatchiri @Ignister": [
    "SR"
  ],
  "Machina Metalcruncher": [
    "UR"
  ],
  "Superheavy Samurai Swordmaster Musashi": [
    "C"
  ],
  "Effect Veiler": [
    "StR"
  ]
}