{
  "Relinquished": [
    "Common"
  ],
  "Millennium-Eyes Illusionist": [
    "Ultra Rare"
  ],
  "Illusionist Faceless Magician": [
    "Rare"
  ],
  "Millennium-Eyes Restrict": [
    "Ultra Rare"
  ],
  "Relinquished Fusion": [
    "Ultra Rare"
  ],
  "Thousand-Eyes Restrict": [
    "Common"
  ],
  "Black Illusion Ritual": [
    "Common"
  ],
  "Parasite Paranoid": [
    "Rare"
  ],
  "Metamorphosed Insect Queen": [
    "Super Rare"
  ],
  "Cocoon of Ultra Evolution": [
    "Ultra Rare"
  ],
  "Corrosive Scales": [
    "Rare"
  ],
  "Pinch Hopper": [
    "Common"
  ],
  "Insect Queen": [
    "Common"
  ],
  "Perfectly Ultimate Great Moth": [
    "Common"
  ],
  "BM-4 Blast Spider": [
    "Rare"
  ],
  "Desperado Barrel Dragon": [
    "Ultra Rare"
  ],
  "Heavy Metal Raiders": [
    "Super Rare"
  ],
  "Proton Blast": [
    "Super Rare"
  ],
  "Blast Sphere": [
    "Common"
  ],
  "Barrel Dragon": [
    "Common"
  ],
  "Time Machine": [
    "Common"
  ],
  "Armed Dragon Catapult Cannon": [
    "Super Rare"
  ],
  "Ojamassimilation": [
    "Rare"
  ],
  "Ojamatch": [
    "Rare"
  ],
  "Ojama Pajama": [
    "Rare"
  ],
  "Armed Dragon LV3": [
    "Common"
  ],
  "Armed Dragon LV5": [
    "Common"
  ],
  "Armed Dragon LV7": [
    "Common"
  ],
  "VWXYZ-Dragon Catapult Cannon": [
    "Common"
  ],
  "Ojamagic": [
    "Common"
  ],
  "Ancient Gear Frame": [
    "Rare"
  ],
  "Ancient Gear Megaton Golem": [
    "Super Rare"
  ],
  "Ancient Gear Fusion": [
    "Ultra Rare"
  ],
  "Cross-Dimensional Duel": [
    "Super Rare"
  ],
  "Ancient Gear Golem": [
    "Common"
  ],
  "Ancient Gear Golem - Ultimate Pound": [
    "Common"
  ],
  "Ultimate Ancient Gear Golem": [
    "Common"
  ],
  "Rainbow Overdragon": [
    "Super Rare"
  ],
  "Rainbow Bridge": [
    "Ultra Rare"
  ],
  "Crystal Bond": [
    "Ultra Rare"
  ],
  "Ultimate Crystal Magic": [
    "Super Rare"
  ],
  "Crystal Beast Ruby Carbuncle": [
    "Common"
  ],
  "Crystal Beast Sapphire Pegasus": [
    "Common"
  ],
  "Rainbow Dragon": [
    "Common"
  ],
  "Crystal Release": [
    "Common"
  ],
  "Crystal Tree": [
    "Common"
  ],
  "Vortex Trooper": [
    "Common"
  ],
  "Panzer Dragon": [
    "Common"
  ],
  "Instant Fusion": [
    "Common"
  ],
  "Limiter Removal": [
    "Common"
  ],
  "Worm Bait": [
    "Common"
  ],
  "Mimicat": [
    "Rare"
  ],
  "Toon Kingdom": [
    "Rare"
  ]
}