{
  "19PR-JP001": [
    "Shiny Black \"C\" Squadder"
  ],
  "19PR-JP002": [
    "Astra Ghouls"
  ],
  "19PR-JP003": [
    "Rain Bozu"
  ],
  "19PR-JP004": [
    "Bellcat Fighter"
  ],
  "19PR-JP005": [
    "Link Party"
  ],
  "19PR-JP006": [
    "Matching Outfits"
  ],
  "19PR-JP007": [
    "Link Apple"
  ],
  "19PR-JP008": [
    "Flying Red Carp"
  ],
  "19PR-JP009": [
    "Shinobi Insect Hagakuremino"
  ],
  "19PR-JP010": [
    "Two Toads with One Sting"
  ],
  "19PR-JP011": [
    "Dances with Beasts"
  ],
  "19PR-JP012": [
    "Token (card)"
  ]
}