{
  "Cocoon of Ultra Evolution (Skill Card)": [
    "Common"
  ],
  "Inner Conflict": [
    "Common"
  ],
  "Twisted Personality": [
    "Common"
  ],
  "Dark Ruler Ha Des": [
    "Ultra Rare"
  ],
  "Lava Golem": [
    "Ultra Rare"
  ],
  "Charging Gaia the Fierce Knight": [
    "Ultra Rare"
  ],
  "Toon Dark Magician": [
    "Ultra Rare"
  ],
  "Allure of Darkness": [
    "Ultra Rare"
  ],
  "Skull Servant": [
    "Super Rare"
  ],
  "Queen's Knight": [
    "Super Rare"
  ],
  "Black Luster Soldier": [
    "Super Rare"
  ],
  "Toon World": [
    "Super Rare"
  ],
  "Offerings to the Doomed": [
    "Super Rare"
  ],
  "Windstorm of Etaqua": [
    "Super Rare"
  ],
  "Nightmare Wheel": [
    "Super Rare"
  ],
  "Zoma the Spirit": [
    "Super Rare"
  ],
  "Waking the Dragon": [
    "Super Rare"
  ],
  "King's Knight": [
    "Common"
  ],
  "D.D. Crow": [
    "Common"
  ],
  "Golden Ladybug": [
    "Common"
  ],
  "Santa Claws": [
    "Common"
  ],
  "Zombina": [
    "Common"
  ],
  "Parasite Paranoid": [
    "Common"
  ],
  "Meteor Black Dragon": [
    "Common"
  ],
  "Ryu Senshi": [
    "Common"
  ],
  "Arcana Knight Joker": [
    "Common"
  ],
  "Fusion Gate": [
    "Common"
  ],
  "Order to Charge": [
    "Common"
  ],
  "Advanced Ritual Art": [
    "Common"
  ],
  "Shard of Greed": [
    "Common"
  ],
  "Bashing Shield": [
    "Common"
  ],
  "Dust Tornado": [
    "Common"
  ],
  "Haunted Shrine": [
    "Common"
  ],
  "The Golden Apples": [
    "Common"
  ],
  "Token (card)": [
    "Super Rare"
  ]
}