{
  "Infernal Flame Emperor": [
    "UR"
  ],
  "Great Angus": [
    "C"
  ],
  "Blazing Inpachi": [
    "C"
  ],
  "UFO Turtle": [
    "C"
  ],
  "Little Chimera": [
    "C"
  ],
  "Inferno": [
    "C"
  ],
  "Molten Zombie": [
    "C"
  ],
  "Solar Flare Dragon": [
    "C"
  ],
  "Ultimate Baseball Kid": [
    "C"
  ],
  "Raging Flame Sprite": [
    "C"
  ],
  "Thestalos the Firestorm Monarch": [
    "C"
  ],
  "Gaia Soul the Combustible Collective": [
    "C"
  ],
  "Fox Fire": [
    "C"
  ],
  "Snatch Steal": [
    "C"
  ],
  "Mystical Space Typhoon": [
    "C"
  ],
  "Molten Destruction": [
    "C"
  ],
  "Nobleman of Crossout": [
    "C"
  ],
  "Premature Burial": [
    "C"
  ],
  "Pot of Greed": [
    "C"
  ],
  "Tribute to The Doomed": [
    "C"
  ],
  "Heavy Storm": [
    "C"
  ],
  "Dark Room of Nightmare": [
    "C"
  ],
  "Reload": [
    "C"
  ],
  "Level Limit - Area B": [
    "C"
  ],
  "Necklace of Command": [
    "C"
  ],
  "Meteor of Destruction": [
    "C"
  ],
  "Dust Tornado": [
    "C"
  ],
  "Call of the Haunted": [
    "C"
  ],
  "Jar of Greed": [
    "C"
  ],
  "Spell Shield Type-8": [
    "C"
  ],
  "Backfire": [
    "C"
  ]
}