{
  "Fire King High Avatar Garunix": [
    "Ultra Rare"
  ],
  "Fire King Avatar Barong": [
    "Rare"
  ],
  "Fire King Avatar Kirin": [
    "Rare"
  ],
  "Sacred Phoenix of Nephthys": [
    "Common"
  ],
  "Manticore of Darkness": [
    "Common"
  ],
  "Goka, the Pyre of Malice": [
    "Common"
  ],
  "Hazy Flame Hyppogrif": [
    "Common"
  ],
  "Laval Lancelord": [
    "Common"
  ],
  "Flamvell Firedog": [
    "Common"
  ],
  "Flamvell Poun": [
    "Common"
  ],
  "Jurrac Guaiba": [
    "Common"
  ],
  "Jurrac Velo": [
    "Common"
  ],
  "Volcanic Rocket": [
    "Common"
  ],
  "Volcanic Counter": [
    "Common"
  ],
  "Molten Zombie": [
    "Common"
  ],
  "Spirit of Flames": [
    "Common"
  ],
  "Raging Flame Sprite": [
    "Common"
  ],
  "Fox Fire": [
    "Common"
  ],
  "Flame Tiger": [
    "Common"
  ],
  "Little Chimera": [
    "Common"
  ],
  "UFO Turtle": [
    "Common"
  ],
  "Onslaught of the Fire Kings": [
    "Super Rare"
  ],
  "Circle of the Fire Kings": [
    "Super Rare"
  ],
  "Rekindling": [
    "Common"
  ],
  "Blaze Accelerator": [
    "Common"
  ],
  "Wild Nature's Release": [
    "Common"
  ],
  "Pot of Duality": [
    "Common"
  ],
  "Hand Destruction": [
    "Common"
  ],
  "Creature Swap": [
    "Common"
  ],
  "Burden of the Mighty": [
    "Common"
  ],
  "Backfire": [
    "Common"
  ],
  "Flamvell Counter": [
    "Common"
  ],
  "Phoenix Wing Wind Blast": [
    "Common"
  ],
  "Horn of the Phantom Beast": [
    "Common"
  ],
  "Blast with Chain": [
    "Common"
  ],
  "Spiritual Fire Art - Kurenai": [
    "Common"
  ],
  "Regretful Rebirth": [
    "Common"
  ],
  "Chain Destruction": [
    "Common"
  ],
  "Nightmare Wheel": [
    "Common"
  ]
}